{
    "provider": {
        "aws": {
            "region": "${var.region_name}",
            "access_key": "${var.aws_access_key}",
            "secret_key": "${var.aws_secret_key}"
        }
    },
    "module": {
        "network-vpc": {
            "source": "../../../../modules/aws/network",
            "name": "${var.deployment_name}-${var.env}",
            "vpc_cidr": "${var.vpc_cidr}",
            "resource_tags" : {},
            "subnets_cidrs": "${var.subnets}",
            "bastion_subnet_cidr": "${var.bastion_subnet}",
            "private_conf": "${var.private_conf}",
            "client_enabled": "${var.client_enabled}"
        },
        "keypair": {
            "source": "../../../../modules/aws/keypair",
            "name": "${var.deployment_name}-${var.env}",
            "ssh_public_key": "${var.ssh_public_key}",
            "resource_tags" : {}
        },
        "rs-cluster": {
            "source": "../../../../modules/aws/re",
            "name": "${var.deployment_name}-${var.env}",
            "worker_count": "${var.cluster_size}",
            "machine_type": "${var.machine_type}",
            "machine_image": "${var.machine_image}",
            "resource_tags" : {},
            "ssh_user": "${var.ssh_user}",
            "ssh_public_key": "${var.ssh_public_key}",
            "ssh_key_name": "${module.keypair.key-name}",
            "security_groups": "${module.network-vpc.security-groups}",
            "availability_zones": "${keys(var.subnets)}",
            "rack_aware" : "${var.rack_aware}",
            "subnets": "${module.network-vpc.subnets}",
            "private_conf": "${var.private_conf}",
            "cluster_dns" : "cluster.${var.env}-${var.deployment_name}.${var.hosted_zone}",
            "redis_distro" : "${var.rs_release}",
            "boot_disk_size" : "${var.volume_size}",
            "boot_disk_type" : "${var.volume_type}",
            "redis_user" : "${var.rs_user}",
            "redis_password" : "${var.rs_password}"
        },
        "rs-client": {
            "source": "../../../../modules/aws/bastion",
            "name": "${var.deployment_name}-${var.env}",
            "subnet": "${module.network-vpc.bastion-subnet[0].id}",
            "availability_zone": "${keys(var.bastion_subnet)[0]}",
            "security_groups": "${module.network-vpc.bastion-security-groups}",
            "machine_image": "${var.machine_image}",
            "machine_type": "${var.machine_type}",
            "memtier_package": "${var.memtier_package}",
            "redis_stack_package": "${var.redis_stack_package}",
            "promethus_package": "${var.promethus_package}",
            "cluster_dns": "${module.rs-cluster-dns.cluster_dns}",
            "boot_disk_size" : "${var.volume_size}",
            "boot_disk_type" : "${var.volume_type}",
            "resource_tags" : {},
            "ssh_user": "${var.ssh_user}",
            "ssh_public_key": "${var.ssh_public_key}",
            "ssh_key_name": "${module.keypair.key-name}"
        },
        "rs-cluster-dns": {
            "source": "../../../../modules/aws/ns-public",
            "subdomain": "${var.env}-${var.deployment_name}",
            "hosted_zone": "${var.hosted_zone}",
            "resource_tags": {},
            "ip_addresses": "${module.rs-cluster.re-public-ips}"  
        }
    },
    "output": {
        "rs-client-public-IP": {
            "value": "${module.rs-client.public-ip}"
        },
        "rs-prometheus-endpoint": {
            "value": "${module.rs-client.prometheus-endpoint}"
        },
        "rs-grafana-endpoint": {
            "value": "${module.rs-client.grafana-endpoint}"
        },
        "rs-cluster-public-ips": {
            "value": "${module.rs-cluster.re-public-ips}"
        },
        "rs-cluster-nodes-dns": {
            "value": "${module.rs-cluster-dns.A-records}"
        },
        "rs-cluster-ui-dns": {
            "value": ["https://${module.rs-cluster-dns.cluster_master_dns}:8443",
                  "https://${module.rs-cluster-dns.cluster_dns}:8443"]
        }
    }
}